hydropt/__init__.py
hydropt/_version.py
hydropt/band_models.py
hydropt/bio_optics.py
hydropt/hydropt.py
hydropt/utils.py
hydropt/data/PACE_polynom_04_h2o.csv
hydropt/data/PACE_polynom_05.csv
hydropt/data/phyto_siop.csv
hydropt/data/psc_absorption_se_uitz_2008.csv
hydropt/data/water_mason016.csv
hydropt_oc-0.3.3.dist-info/LICENSE
hydropt_oc-0.3.3.dist-info/METADATA
hydropt_oc-0.3.3.dist-info/WHEEL
hydropt_oc-0.3.3.dist-info/top_level.txt
hydropt_oc-0.3.3.dist-info/RECORD
