Metadata-Version: 2.1
Name: hydropt-oc
Version: 0.3.3
Summary: HYDROPT: a Python Framework for Fast Inverse Modelling of
Home-page: https://github.com/tadz-io/hydropt
Author: Tadzio Holtrop
Author-email: tadzio.holtrop@icloud.com
License: AGPL-3.0
Platform: UNKNOWN
License-File: LICENSE
Requires-Dist: numpy
Requires-Dist: pandas
Requires-Dist: matplotlib
Requires-Dist: scikit-learn
Requires-Dist: xarray
